[
  {
    "id": "1776054512564",
    "userId": "30614",
    "name": "신헌제",
    "date": "2026-04-13",
    "startTime": "16:50",
    "endTime": "18:00",
    "seatType": "single",
    "seatTypeLabel": "1인석",
    "seatId": "single-8",
    "seatLabel": "8번",
    "peopleCount": 1,
    "memberIds": [],
    "cancelled": true,
    "createdAt": "2026-04-13T04:28:32.564Z"
  },
  {
    "id": "1776054548380",
    "userId": "30614",
    "name": "신헌제",
    "date": "2026-04-13",
    "startTime": "19:00",
    "endTime": "20:20",
    "seatType": "single",
    "seatTypeLabel": "1인석",
    "seatId": "single-9",
    "seatLabel": "9번",
    "peopleCount": 1,
    "memberIds": [],
    "cancelled": true,
    "createdAt": "2026-04-13T04:29:08.380Z"
  },
  {
    "id": "1776054552354",
    "userId": "30614",
    "name": "신헌제",
    "date": "2026-04-13",
    "startTime": "20:40",
    "endTime": "22:00",
    "seatType": "single",
    "seatTypeLabel": "1인석",
    "seatId": "single-13",
    "seatLabel": "13번",
    "peopleCount": 1,
    "memberIds": [],
    "cancelled": true,
    "createdAt": "2026-04-13T04:29:12.354Z"
  },
  {
    "id": "1776057335692",
    "userId": "30614",
    "name": "신헌제",
    "date": "2026-04-13",
    "startTime": "16:50",
    "endTime": "18:00",
    "seatType": "single",
    "seatTypeLabel": "1인석",
    "seatId": "single-12",
    "seatLabel": "12번",
    "peopleCount": 1,
    "memberIds": [],
    "cancelled": true,
    "createdAt": "2026-04-13T05:15:35.692Z"
  }
]